unfold/__init__.py
unfold/admin.py
unfold/apps.py
unfold/checks.py
unfold/contrib/__init__.py
unfold/contrib/filters/__init__.py
unfold/contrib/filters/admin.py
unfold/contrib/filters/apps.py
unfold/contrib/filters/forms.py
unfold/contrib/filters/static/unfold/filters/css/nouislider.min.css
unfold/contrib/filters/static/unfold/filters/js/DateTimeShortcuts.js
unfold/contrib/filters/static/unfold/filters/js/admin-numeric-filter.js
unfold/contrib/filters/static/unfold/filters/js/nouislider.min.js
unfold/contrib/filters/static/unfold/filters/js/wNumb.min.js
unfold/contrib/filters/templates/unfold/filters/filters_date_range.html
unfold/contrib/filters/templates/unfold/filters/filters_datetime_range.html
unfold/contrib/filters/templates/unfold/filters/filters_numeric_range.html
unfold/contrib/filters/templates/unfold/filters/filters_numeric_single.html
unfold/contrib/filters/templates/unfold/filters/filters_numeric_slider.html
unfold/contrib/forms/__init__.py
unfold/contrib/forms/apps.py
unfold/contrib/forms/static/unfold/forms/css/trix.css
unfold/contrib/forms/static/unfold/forms/js/trix.config.js
unfold/contrib/forms/static/unfold/forms/js/trix.js
unfold/contrib/forms/templates/unfold/forms/helpers/toolbar.html
unfold/contrib/forms/templates/unfold/forms/wysiwyg.html
unfold/contrib/forms/widgets.py
unfold/contrib/guardian/__init__.py
unfold/contrib/guardian/apps.py
unfold/contrib/guardian/templates/admin/guardian/model/change_form.html
unfold/contrib/guardian/templates/admin/guardian/model/field.html
unfold/contrib/guardian/templates/admin/guardian/model/obj_perms_manage.html
unfold/contrib/guardian/templates/admin/guardian/model/obj_perms_manage_group.html
unfold/contrib/guardian/templates/admin/guardian/model/obj_perms_manage_user.html
unfold/contrib/guardian/templates/unfold/guardian/group_form.html
unfold/contrib/guardian/templates/unfold/guardian/user_form.html
unfold/contrib/import_export/__init__.py
unfold/contrib/import_export/admin.py
mw_django_unfold-0.20.3.dist-info/LICENSE.md
mw_django_unfold-0.20.3.dist-info/METADATA
mw_django_unfold-0.20.3.dist-info/WHEEL
mw_django_unfold-0.20.3.dist-info/RECORD
