Metadata-Version: 2.1
Name: mw-django-unfold
Version: 0.20.3
Summary: Modern Django admin theme for seamless interface development
Home-page: https://unfoldadmin.com
License: MIT
Keywords: django,admin,tailwind,theme
Requires-Python: >=3.8
Classifier: Environment :: Web Environment
Classifier: Framework :: Django
Classifier: Intended Audience :: Developers
Classifier: License :: OSI Approved :: MIT License
Classifier: Operating System :: OS Independent
Classifier: Programming Language :: Python
Classifier: Programming Language :: Python :: 3
Classifier: Programming Language :: Python :: 3.8
Classifier: Programming Language :: Python :: 3.9
Classifier: Programming Language :: Python :: 3.10
Classifier: Programming Language :: Python :: 3.11
Classifier: Programming Language :: Python :: 3.12
Requires-Dist: django (>=3.2)
Project-URL: Repository, https://github.com/MwPersonal/django-unfold
